hera_sim/__init__.py
hera_sim/__yaml_constructors.py
hera_sim/adjustment.py
hera_sim/antpos.py
hera_sim/beams.py
hera_sim/cli_utils.py
hera_sim/components.py
hera_sim/defaults.py
hera_sim/eor.py
hera_sim/foregrounds.py
hera_sim/interpolators.py
hera_sim/io.py
hera_sim/noise.py
hera_sim/rfi.py
hera_sim/sigchain.py
hera_sim/simulate.py
hera_sim/utils.py
hera_sim/vis.py
hera_sim/config/H1C.yaml
hera_sim/config/H2C.yaml
hera_sim/config/__init__.py
hera_sim/config/debug.yaml
hera_sim/data/H37_FR_Filters_small.npz
hera_sim/data/HERA_H1C_BANDPASS.npy
hera_sim/data/HERA_H1C_BEAM_INTEGRALS.npz
hera_sim/data/HERA_H1C_BEAM_POLY.npy
hera_sim/data/HERA_H1C_REFLECTIONS.npz
hera_sim/data/HERA_H1C_RFI_STATIONS.npy
hera_sim/data/HERA_H2C_BANDPASS.npy
hera_sim/data/HERA_H2C_BEAM_MODEL.npz
hera_sim/data/HERA_H2C_BEAM_POLY.npy
hera_sim/data/HERA_H2C_RFI_STATIONS.npy
hera_sim/data/HERA_H4C_BANDPASS.npz
hera_sim/data/HERA_H4C_BEAM_INTEGRALS.npz
hera_sim/data/HERA_H4C_REFLECTIONS.npz
hera_sim/data/HERA_LAT_LON_ALT.npy
hera_sim/data/HERA_Tsky_Reformatted.npz
hera_sim/data/HERA_Tsky_vs_LST.npz
hera_sim/data/tutorials_data/end_to_end/array_layout.csv
hera_sim/data/tutorials_data/end_to_end/make_mock_catalog.py
hera_sim/data/tutorials_data/end_to_end/obsparams.yaml
hera_sim/data/tutorials_data/end_to_end/sample_catalog.txt
hera_sim/data/tutorials_data/end_to_end/telescope.yaml
hera_sim/data/tutorials_data/visibility_simulator/antenna_layout_hera_phase1.csv
hera_sim/data/tutorials_data/visibility_simulator/gleam_top50.skyh5
hera_sim/data/tutorials_data/visibility_simulator/obsparam_hera_phase1_gleam_top50.yaml
hera_sim/data/tutorials_data/visibility_simulator/telescope_config_hera_airy.yaml
hera_sim/tests/conftest.py
hera_sim/tests/test_adjustment.py
hera_sim/tests/test_antpos.py
hera_sim/tests/test_beams.py
hera_sim/tests/test_cli_utils.py
hera_sim/tests/test_components.py
hera_sim/tests/test_defaults.py
hera_sim/tests/test_eor.py
hera_sim/tests/test_foregrounds.py
hera_sim-4.3.1.dist-info/AUTHORS.rst
hera_sim-4.3.1.dist-info/LICENSE.rst
hera_sim-4.3.1.dist-info/METADATA
hera_sim-4.3.1.dist-info/WHEEL
hera_sim-4.3.1.dist-info/top_level.txt
hera_sim-4.3.1.dist-info/RECORD
