Metadata-Version: 2.2
Name: hera_sim
Version: 4.3.1
Summary: A collection of simulation routines describing the HERA instrument.
Author: HERA Team
Author-email: Steven Murray <murray.steveng@gmail.com>
License: MIT
Project-URL: Documentation, https://hera_sim.readthedocs.org
Project-URL: Repository, https://github.com/HERA-Team/hera_sim
Classifier: Development Status :: 4 - Beta
Classifier: Intended Audience :: Science/Research
Classifier: License :: OSI Approved
Classifier: License :: OSI Approved :: MIT License
Classifier: Natural Language :: English
Classifier: Programming Language :: Python :: 3
Classifier: Programming Language :: Python :: 3 :: Only
Classifier: Topic :: Scientific/Engineering :: Astronomy
Classifier: Topic :: Scientific/Engineering :: Physics
Requires-Python: >=3.10
License-File: LICENSE.rst
License-File: AUTHORS.rst
Requires-Dist: astropy
Requires-Dist: astropy-healpix
Requires-Dist: cached-property
Requires-Dist: deprecation
Requires-Dist: hera-cli-utils>=0.1.0
Requires-Dist: numpy>=2
Requires-Dist: pyuvdata>=3.1.2
Requires-Dist: pyuvsim>=1.4
Requires-Dist: pyyaml>=5.1
Requires-Dist: rich
Requires-Dist: scipy
Requires-Dist: typing-extensions; python_version < "3.11"
Provides-Extra: all
Requires-Dist: hera-sim[bda,cal,gpu,vis]; extra == "all"
Provides-Extra: bda
Requires-Dist: bda; extra == "bda"
Provides-Extra: cal
Requires-Dist: hera-calibration>3.6.1; extra == "cal"
Provides-Extra: dev
Requires-Dist: hera-sim[docs,tests]; extra == "dev"
Provides-Extra: docs
Requires-Dist: fftvis; extra == "docs"
Requires-Dist: furo; extra == "docs"
Requires-Dist: ipython; extra == "docs"
Requires-Dist: matvis>=1.3.0; extra == "docs"
Requires-Dist: nbsphinx; extra == "docs"
Requires-Dist: numpydoc>=0.8; extra == "docs"
Requires-Dist: pyradiosky>=0.1.2; extra == "docs"
Requires-Dist: sphinx<7.2,>=1.8; extra == "docs"
Requires-Dist: sphinx-autorun; extra == "docs"
Provides-Extra: tests
Requires-Dist: coverage>=4.5.1; extra == "tests"
Requires-Dist: hera-sim[bda,cal,vis]; extra == "tests"
Requires-Dist: matplotlib>=3.4.2; extra == "tests"
Requires-Dist: pre-commit; extra == "tests"
Requires-Dist: pytest>=3.5.1; extra == "tests"
Requires-Dist: pytest-cov>=2.5.1; extra == "tests"
Requires-Dist: uvtools; extra == "tests"
Provides-Extra: vis
Requires-Dist: fftvis>=0.1.0; extra == "vis"
Requires-Dist: line-profiler; extra == "vis"
Requires-Dist: matvis>=1.2.1; extra == "vis"
Requires-Dist: mpi4py; extra == "vis"
Requires-Dist: pyradiosky>=0.1.2; extra == "vis"
